django_pg_rrule/__init__.py
django_pg_rrule/fields.py
django_pg_rrule/managers.py
django_pg_rrule/models.py
django_pg_rrule/operations.py
django_pg_rrule/test_app/__init__.py
django_pg_rrule/test_app/apps.py
django_pg_rrule/test_app/migrations/0001_initial.py
django_pg_rrule/test_app/migrations/__init__.py
django_pg_rrule/test_app/models.py
django_pg_rrule/test_app/settings.py
django_pg_rrule/test_model.py
django_pg_rrule-0.4.2.dist-info/METADATA
django_pg_rrule-0.4.2.dist-info/WHEEL
django_pg_rrule-0.4.2.dist-info/RECORD
