Metadata-Version: 2.3
Name: django-pg-rrule
Version: 0.4.2
Summary: 
License: BSD-3-Clause
Author: Jonathan Weth
Author-email: dev@jonathanweth.de
Requires-Python: >=3.10,<4.0
Classifier: License :: OSI Approved :: BSD License
Classifier: Programming Language :: Python :: 3
Classifier: Programming Language :: Python :: 3.10
Classifier: Programming Language :: Python :: 3.11
Classifier: Programming Language :: Python :: 3.12
Classifier: Programming Language :: Python :: 3.13
Requires-Dist: Django (>4.0)
Requires-Dist: django-cte (>=1.3.2,<2.0.0)
